src/alu.v
module alu(
    input [31:0] a,
    input [31:0] b,
    input [2:0] alu_op,

    output reg [31:0] result
);

always @(*) begin

    case(alu_op)

        3'b000:
            result = a + b;

        3'b001:
            result = a - b;

        3'b010:
            result = a & b;

        3'b011:
            result = a | b;

        3'b100:
            result = a ^ b;

        default:
            result = 32'd0;

    endcase

end

endmodule

src/register_file.v
module register_file(

    input clk,

    input [4:0] rs1,
    input [4:0] rs2,

    input [4:0] rd,
    input reg_write,

    input [31:0] write_data,

    output [31:0] read_data1,
    output [31:0] read_data2

);

reg [31:0] registers [0:31];

initial begin
    registers[1] = 10;
    registers[2] = 5;
end

assign read_data1 = registers[rs1];
assign read_data2 = registers[rs2];

always @(posedge clk)
begin
    if(reg_write) begin
        registers[rd] <= write_data;

        $display(
        "x1=%d x2=%d rd=%d write_data=%d",
        registers[1],
        registers[2],
        rd,
        write_data
        );
    end
end

endmodule

src/datapath.v
module datapath(

    input clk,
    input [2:0] alu_op,
    input [31:0] instruction,

    output [31:0] result

);

wire [31:0] read_data1;
wire [31:0] read_data2;
wire [31:0] alu_result;

register_file RF(

    .clk(clk),

    .rs1(instruction[19:15]),
    .rs2(instruction[24:20]),

    .rd(instruction[11:7]),

    .reg_write(1'b1),

    .write_data(alu_result),

    .read_data1(read_data1),
    .read_data2(read_data2)

);

alu ALU(

    .a(read_data1),
    .b(read_data2),

    .alu_op(alu_op),

    .result(alu_result)

);

assign result = alu_result;

endmodule

src/control_unit.v
module control_unit (
    input [31:0] instruction,
    output reg [2:0] alu_op
) ;

always @(*) begin

    if(instruction[6:0] == 7'b0110011) begin

        if(instruction[14:12] == 3'b000 &&
           instruction[31:25] == 7'b0000000)

            alu_op = 3'b000; // ADD

        else if(instruction[14:12] == 3'b000 &&
                instruction[31:25] == 7'b0100000)

            alu_op = 3'b001; // SUB

        else if(instruction[14:12] == 3'b111)

            alu_op = 3'b010; // AND

        else if(instruction[14:12] == 3'b110)

            alu_op = 3'b011; // OR

        else if(instruction[14:12] == 3'b100)

            alu_op = 3'b100; // XOR

        else

            alu_op = 3'b000;

    end

    else

        alu_op = 3'b000;

end
endmodule

src/instruction_memory.v
module instruction_memory (
    input [31:0] address,
    output  [31:0] instruction
); 
    reg [31:0] memory [0:15]; 
    initial begin

    

    memory[0] =
    32'b0000000_00010_00001_000_00011_0110011; // ADD x3,x1,x2

    memory[1] =
    32'b0100000_00010_00001_000_00100_0110011; // SUB x4,x1,x2

    memory[2] =
    32'b0000000_00010_00001_111_00101_0110011; // AND x5,x1,x2

    memory[3] =
    32'b0000000_00010_00001_110_00110_0110011; // OR x6,x1,x2

    memory[4] =
    32'b0000000_00010_00001_100_00111_0110011; // XOR x7,x1,x2


    end
    assign instruction = memory[address >> 2];
endmodule

src/pc.v
module pc (
    input clk , reset , 
    output reg [31:0] pc_out);

    always @(posedge clk or posedge reset) 
    begin 
        if (reset) 
           pc_out <= 32'd0;
        else 
           pc_out <= pc_out + 4;
    end

    
endmodule

src/cpu_top.v
module cpu_top 
    (
    input clk ,
    input reset ,
    output [31:0] instruction ,
    output [31:0] pc_out
    ) ;
    wire [31:0] pc_address ;
    pc PC (
        .clk(clk) ,
        .reset(reset) ,
        .pc_out(pc_address)
    ) ;
    instruction_memory IM (
        .address(pc_address) ,
        .instruction(instruction)
    ) ;
    assign pc_out = pc_address ;
endmodule

src/simple_cpu.v
module simple_cpu(

    input clk,
    input reset,

    output [31:0] pc_out,
    output [31:0] instruction,
    output [2:0] alu_op,
    output [31:0] result

);

wire [31:0] instruction_wire;
wire [2:0] alu_op_wire;

cpu_top CPU(
    .clk(clk),
    .reset(reset),
    .pc_out(pc_out),
    .instruction(instruction_wire)
);

control_unit CU(
    .instruction(instruction_wire),
    .alu_op(alu_op_wire)
);

datapath DP(
    .clk(clk),
    .alu_op(alu_op_wire),
    .instruction(instruction_wire),
    .result(result)
);

assign instruction = instruction_wire;
assign alu_op = alu_op_wire;

endmodule

tb/tb_simple_cpu.v
`timescale 1ns/1ps

module tb_simple_cpu;

reg clk;
reg reset;

wire [31:0] pc_out;
wire [31:0] instruction;
wire [2:0] alu_op;
wire [31:0] result;

simple_cpu uut(
    .clk(clk),
    .reset(reset),
    .pc_out(pc_out),
    .instruction(instruction),
    .alu_op(alu_op),
    .result(result)
);

always #5 clk = ~clk;

initial begin

    $dumpfile("simple_cpu.vcd");
    $dumpvars(0,tb_simple_cpu);

    clk = 0;
    reset = 1;

    #10;
    reset = 0;

    #100;

    $finish;

end

endmodule

simple_cpu.vcd
$date
	Tue Jun 23 13:31:04 2026
$end
$version
	Icarus Verilog
$end
$timescale
	1ps
$end
$scope module tb_simple_cpu $end
$var wire 32 ! result [31:0] $end
$var wire 32 " pc_out [31:0] $end
$var wire 32 # instruction [31:0] $end
$var wire 3 $ alu_op [2:0] $end
$var reg 1 % clk $end
$var reg 1 & reset $end
$scope module uut $end
$var wire 3 ' alu_op [2:0] $end
$var wire 1 % clk $end
$var wire 32 ( instruction [31:0] $end
$var wire 1 & reset $end
$var wire 32 ) result [31:0] $end
$var wire 32 * pc_out [31:0] $end
$var wire 32 + instruction_wire [31:0] $end
$var wire 3 , alu_op_wire [2:0] $end
$scope module CPU $end
$var wire 1 % clk $end
$var wire 32 - pc_out [31:0] $end
$var wire 1 & reset $end
$var wire 32 . pc_address [31:0] $end
$var wire 32 / instruction [31:0] $end
$scope module IM $end
$var wire 32 0 instruction [31:0] $end
$var wire 32 1 address [31:0] $end
$upscope $end
$scope module PC $end
$var wire 1 % clk $end
$var wire 1 & reset $end
$var reg 32 2 pc_out [31:0] $end
$upscope $end
$upscope $end
$scope module CU $end
$var wire 32 3 instruction [31:0] $end
$var reg 3 4 alu_op [2:0] $end
$upscope $end
$scope module DP $end
$var wire 3 5 alu_op [2:0] $end
$var wire 1 % clk $end
$var wire 32 6 instruction [31:0] $end
$var wire 32 7 result [31:0] $end
$var wire 32 8 read_data2 [31:0] $end
$var wire 32 9 read_data1 [31:0] $end
$var wire 32 : alu_result [31:0] $end
$scope module ALU $end
$var wire 3 ; alu_op [2:0] $end
$var wire 32 < b [31:0] $end
$var wire 32 = a [31:0] $end
$var reg 32 > result [31:0] $end
$upscope $end
$scope module RF $end
$var wire 1 % clk $end
$var wire 5 ? rd [4:0] $end
$var wire 32 @ read_data1 [31:0] $end
$var wire 32 A read_data2 [31:0] $end
$var wire 1 B reg_write $end
$var wire 5 C rs1 [4:0] $end
$var wire 5 D rs2 [4:0] $end
$var wire 32 E write_data [31:0] $end
$upscope $end
$upscope $end
$upscope $end
$upscope $end
$enddefinitions $end
$comment Show the parameter values. $end
$dumpall
$end
#0
$dumpvars
b1111 E
b10 D
b1 C
1B
b101 A
b1010 @
b11 ?
b1111 >
b1010 =
b101 <
b0 ;
b1111 :
b1010 9
b101 8
b1111 7
b1000001000000110110011 6
b0 5
b0 4
b1000001000000110110011 3
b0 2
b0 1
b1000001000000110110011 0
b1000001000000110110011 /
b0 .
b0 -
b0 ,
b1000001000000110110011 +
b0 *
b1111 )
b1000001000000110110011 (
b0 '
1&
0%
b0 $
b1000001000000110110011 #
b0 "
b1111 !
$end
#5000
1%
#10000
0%
0&
#15000
b101 !
b101 )
b101 7
b101 :
b101 >
b101 E
b1 $
b1 '
b1 ,
b1 4
b1 5
b1 ;
b100 ?
b1000000001000001000001000110011 #
b1000000001000001000001000110011 (
b1000000001000001000001000110011 +
b1000000001000001000001000110011 /
b1000000001000001000001000110011 0
b1000000001000001000001000110011 3
b1000000001000001000001000110011 6
b100 "
b100 *
b100 -
b100 .
b100 1
b100 2
1%
#20000
0%
#25000
b0 !
b0 )
b0 7
b0 :
b0 >
b0 E
b10 $
b10 '
b10 ,
b10 4
b10 5
b10 ;
b101 ?
b1000001111001010110011 #
b1000001111001010110011 (
b1000001111001010110011 +
b1000001111001010110011 /
b1000001111001010110011 0
b1000001111001010110011 3
b1000001111001010110011 6
b1000 "
b1000 *
b1000 -
b1000 .
b1000 1
b1000 2
1%
#30000
0%
#35000
b1111 !
b1111 )
b1111 7
b1111 :
b1111 >
b1111 E
b11 $
b11 '
b11 ,
b11 4
b11 5
b11 ;
b110 ?
b1000001110001100110011 #
b1000001110001100110011 (
b1000001110001100110011 +
b1000001110001100110011 /
b1000001110001100110011 0
b1000001110001100110011 3
b1000001110001100110011 6
b1100 "
b1100 *
b1100 -
b1100 .
b1100 1
b1100 2
1%
#40000
0%
#45000
b100 $
b100 '
b100 ,
b100 4
b100 5
b100 ;
b111 ?
b1000001100001110110011 #
b1000001100001110110011 (
b1000001100001110110011 +
b1000001100001110110011 /
b1000001100001110110011 0
b1000001100001110110011 3
b1000001100001110110011 6
b10000 "
b10000 *
b10000 -
b10000 .
b10000 1
b10000 2
1%
#50000
0%
#55000
bx !
bx )
bx 7
bx :
bx >
bx E
b0 $
b0 '
b0 ,
b0 4
b0 5
b0 ;
bx 9
bx =
bx @
bx C
bx 8
bx <
bx A
bx D
bx ?
bx #
bx (
bx +
bx /
bx 0
bx 3
bx 6
b10100 "
b10100 *
b10100 -
b10100 .
b10100 1
b10100 2
1%
#60000
0%
#65000
b11000 "
b11000 *
b11000 -
b11000 .
b11000 1
b11000 2
1%
#70000
0%
#75000
b11100 "
b11100 *
b11100 -
b11100 .
b11100 1
b11100 2
1%
#80000
0%
#85000
b100000 "
b100000 *
b100000 -
b100000 .
b100000 1
b100000 2
1%
#90000
0%
#95000
b100100 "
b100100 *
b100100 -
b100100 .
b100100 1
b100100 2
1%
#100000
0%
#105000
b101000 "
b101000 *
b101000 -
b101000 .
b101000 1
b101000 2
1%
